configurator/__init__.py
configurator/configurator.py
pyconfigurator-0.4.19.dist-info/licenses/LICENSE
pyconfigurator-0.4.19.dist-info/METADATA
pyconfigurator-0.4.19.dist-info/WHEEL
pyconfigurator-0.4.19.dist-info/top_level.txt
pyconfigurator-0.4.19.dist-info/RECORD
